greeklexiconrejuvenator/__init__.py
greeklexiconrejuvenator/main.py
greeklexiconrejuvenator/prompts.py
greeklexiconrejuvenator-2025.12.21151932.dist-info/METADATA
greeklexiconrejuvenator-2025.12.21151932.dist-info/WHEEL
greeklexiconrejuvenator-2025.12.21151932.dist-info/top_level.txt
greeklexiconrejuvenator-2025.12.21151932.dist-info/RECORD
