Metadata-Version: 2.4
Name: greeklexiconrejuvenator
Version: 2025.12.21151932
Summary: A new package designed to analyze user-provided text about ancient Greek terms and generate a structured summary highlighting terms that should be revitalized in modern language. It leverages pattern
Author-email: greeklexiconrejuvenator <hi@eugene.plus>
License: MIT
Project-URL: Homepage, https://github.com/chigwell/greeklexiconrejuvenator
Requires-Python: >=3.9
Requires-Dist: langchain-llm7>=0.0.0
Requires-Dist: llmatch-messages>=0.0.0
Requires-Dist: langchain-core>=0.3.0
